GBARPGMaker/__init__.py
GBARPGMaker/__main__.py
GBARPGMaker/helper_functions.py
GBARPGMaker/jinja_templates/__init__.py
GBARPGMaker/jinja_templates/graphics.c
GBARPGMaker/jinja_templates/graphics.h
GBARPGMaker/jinja_templates/imageData.c
GBARPGMaker/jinja_templates/imageData.h
GBARPGMaker/jinja_templates/main.c
GBARPGMaker-1.4.dist-info/METADATA
GBARPGMaker-1.4.dist-info/WHEEL
GBARPGMaker-1.4.dist-info/top_level.txt
GBARPGMaker-1.4.dist-info/RECORD
