Metadata-Version: 2.1
Name: GBARPGMaker
Version: 1.4
Summary: a program that helps with development of GBA games
Home-page: https://gitlab.com/kockahonza/gbarpgmaker
Author: UNKNOWN
Author-email: UNKNOWN
License: UNKNOWN
Platform: UNKNOWN
Requires-Dist: jinja2
Requires-Dist: wand (==0.5.0)
